.DS_Store
flyable/.DS_Store
flyable/__init__.py
flyable/flyable.py
flyable/library_loader.py
flyable/utils.py
flyable/dyn_lib/__init__.py
flyable/dyn_lib/linux64/BugpointPasses.so
flyable/dyn_lib/linux64/LLVMHello.so
flyable/dyn_lib/linux64/__init__.py
flyable/dyn_lib/linux64/libLLVMAggressiveInstCombine.so
flyable/dyn_lib/linux64/libLLVMAnalysis.so
flyable/dyn_lib/linux64/libLLVMAsmParser.so
flyable/dyn_lib/linux64/libLLVMAsmPrinter.so
flyable/dyn_lib/linux64/libLLVMBinaryFormat.so
flyable/dyn_lib/linux64/libLLVMBitReader.so
flyable/dyn_lib/linux64/libLLVMBitWriter.so
flyable/dyn_lib/linux64/libLLVMBitstreamReader.so
flyable/dyn_lib/linux64/libLLVMCFGuard.so
flyable/dyn_lib/linux64/libLLVMCFIVerify.so
flyable/dyn_lib/linux64/libLLVMCodeGen.so
flyable/dyn_lib/linux64/libLLVMCore.so
flyable/dyn_lib/linux64/libLLVMCoroutines.so
flyable/dyn_lib/linux64/libLLVMCoverage.so
flyable/dyn_lib/linux64/libLLVMDWARFLinker.so
flyable/dyn_lib/linux64/libLLVMDWP.so
flyable/dyn_lib/linux64/libLLVMDebugInfoCodeView.so
flyable/dyn_lib/linux64/libLLVMDebugInfoDWARF.so
flyable/dyn_lib/linux64/libLLVMDebugInfoGSYM.so
flyable/dyn_lib/linux64/libLLVMDebugInfoMSF.so
flyable/dyn_lib/linux64/libLLVMDebugInfoPDB.so
flyable/dyn_lib/linux64/libLLVMDebuginfod.so
flyable/dyn_lib/linux64/libLLVMDemangle.so
flyable/dyn_lib/linux64/libLLVMDiff.so
flyable/dyn_lib/linux64/libLLVMDlltoolDriver.so
flyable/dyn_lib/linux64/libLLVMExecutionEngine.so
flyable/dyn_lib/linux64/libLLVMExegesis.so
flyable/dyn_lib/linux64/libLLVMExegesisX86.so
flyable/dyn_lib/linux64/libLLVMExtensions.so
flyable/dyn_lib/linux64/libLLVMFileCheck.so
flyable/dyn_lib/linux64/libLLVMFrontendOpenACC.so
flyable/dyn_lib/linux64/libLLVMFrontendOpenMP.so
flyable/dyn_lib/linux64/libLLVMFuzzMutate.so
flyable/dyn_lib/linux64/libLLVMGlobalISel.so
flyable/dyn_lib/linux64/libLLVMIRReader.so
flyable/dyn_lib/linux64/libLLVMInstCombine.so
flyable/dyn_lib/linux64/libLLVMInstrumentation.so
flyable/dyn_lib/linux64/libLLVMInterfaceStub.so
flyable-0.0.1.3.dist-info/LICENSE
flyable-0.0.1.3.dist-info/METADATA
flyable-0.0.1.3.dist-info/WHEEL
flyable-0.0.1.3.dist-info/top_level.txt
flyable-0.0.1.3.dist-info/RECORD
