Metadata-Version: 2.1
Name: flyable
Version: 0.0.1.3
Summary: Flyable is a Python compiler that generates optimized native code to improve the performance of Python workloads.
Home-page: https://github.com/FlyableDev/Flyable
Author: FlyableDev
Author-email: contact@flyable.dev
Project-URL: Bug Tracker, https://github.com/FlyableDev/Flyable/issues
Classifier: Programming Language :: Python :: 3
Classifier: License :: OSI Approved :: GNU Affero General Public License v3 or later (AGPLv3+)
Classifier: Operating System :: OS Independent
Requires-Python: >=3.11
License-File: LICENSE
